openai_simple-0.1.0.dist-info/METADATA
openai_simple-0.1.0.dist-info/WHEEL
openai_simple/__init__.py
openai_simple/openai_simple.cpython-310-x86_64-linux-gnu.so
openai_simple-0.1.0.dist-info/RECORD
