Metadata-Version: 2.1
Name: openai-simple
Version: 0.1.0
Classifier: Programming Language :: Rust
Classifier: Programming Language :: Python :: Implementation :: CPython
Classifier: Programming Language :: Python :: Implementation :: PyPy
Summary: A simple way to get response from the ChatGPT 3 model. Written in rust.
Keywords: openai,chatgpt 3,chatgpt3
Author-email: Jonas Blixt <joblixt@gmail.com>
Requires-Python: >=3.7
